LICENSE
MANIFEST.in
README.rst
distribute_setup.py
setup.cfg
setup.py
bin/dammit
dammit/.config.json
dammit/.databases.json
dammit/VERSION
dammit/__init__.py
dammit/annotate.py
dammit/app.py
dammit/blast.py
dammit/common.py
dammit/databases.py
dammit/dependencies.py
dammit/gff.py
dammit/hits.py
dammit/log.py
dammit/parsers.py
dammit/report.py
dammit/tasks.py
dammit.egg-info/PKG-INFO
dammit.egg-info/SOURCES.txt
dammit.egg-info/dependency_links.txt
dammit.egg-info/not-zip-safe
dammit.egg-info/requires.txt
dammit.egg-info/top_level.txt
dammit/fileio/__init__.py
dammit/fileio/base.py
dammit/fileio/maf.py