Metadata-Version: 1.0
Name: dammit
Version: 0.3.1
Summary: dammit!
Home-page: https://github.com/camillescott/dammit
Author: Camille Scott
Author-email: camille.scott.w@gmail.com
License: BSD
Platform: UNKNOWN
